auto_folderize/_init_.py
auto_folderize/core.py
auto_folderize/rules.py
auto_folderize-0.1.0.dist-info/METADATA
auto_folderize-0.1.0.dist-info/WHEEL
auto_folderize-0.1.0.dist-info/top_level.txt
auto_folderize-0.1.0.dist-info/RECORD
