Metadata-Version: 2.4
Name: auto-folderize
Version: 0.1.0
Summary: A simple Python library to organize files into folders by file type
Author-email: Sourav Sandilya <souravsandilya89882@gmail.com>
Requires-Python: >=3.6
